yamja/__init__.py
yamja/yamja.py
yamja-0.3.0.dist-info/METADATA
yamja-0.3.0.dist-info/WHEEL
yamja-0.3.0.dist-info/licenses/LICENSE
yamja-0.3.0.dist-info/RECORD
