Metadata-Version: 2.4
Name: yamja
Version: 0.3.0
Summary: Opinionated library for handling yaml configuration files and jinja2 templates
Project-URL: Homepage, https://github.com/mobarski/yamja
Project-URL: Repository, https://github.com/mobarski/yamja.git
Project-URL: Documentation, https://github.com/mobarski/yamja#readme
Project-URL: Bug Tracker, https://github.com/mobarski/yamja/issues
Author-email: mobarski <mobarski@gmail.com>
License-Expression: MIT
License-File: LICENSE
Keywords: configuration,jinja2,templates,yaml
Classifier: Development Status :: 4 - Beta
Classifier: License :: OSI Approved :: MIT License
Classifier: Operating System :: OS Independent
Classifier: Programming Language :: Python :: 3
Classifier: Programming Language :: Python :: 3.8
Classifier: Topic :: Software Development :: Libraries :: Python Modules
Requires-Python: >=3.8
Requires-Dist: jinja2
Requires-Dist: pyyaml
Provides-Extra: test
Requires-Dist: pytest; extra == 'test'
